Workbook

Sheet TRANSACCIONES
A1: Fecha | B1: Tipo Transacción | C1: Categoría | D1: Entidad | E1: Cuenta Bancaria | F1: Cliente/Proveedor | G1: Concepto | H1: Referencia | I1: Monto USD | J1: Monto CRC | K1: Ingreso/Egreso | L1: Estado | M1: Prioridad | N1: Vencimiento | O1: Notas | P1: ID Transacción | Q1: Fecha Creación | R1: Usuario | S1: Duplicado? | T1: Validación
A2: 45962 | B2: Apertura Inicial | C2: Efectivo | D2: EMPRESA | E2: Promerica USD (40000003881774) | F2: Sistema | G2: Balance inicial Promerica USD | H2: APERTURA-001 | I2: 2999.24 | J2: =I2*507 | K2: =IF(OR(B2="Factura Cliente",B2="Cobro Factura",B2="Depósito Bancario",B2="Inversión",B2="Dividendo",B2="Apertura Inicial"),"Ingreso","Egreso") | L2: Cobrado | M2: BAJA | P2: TRX-00002 | Q2: 45969.189 | R2: SISTEMA | S2: =IF(COUNTIFS($A$2:A1,A2,$F$2:F1,F2,$I$2:I1,I2)>0,"🔴 DUPLICADO EXACTO","") | T2: =IF(AND(A2<>"",B2<>"",D2<>"",E2<>"",I2>0),"✅ OK","❌ FALTA DATO")
A3: 45962 | B3: Apertura Inicial | C3: Efectivo | D3: EMPRESA | E3: BNCR USD (601066-4) | F3: Sistema | G3: Balance inicial BNCR USD | H3: APERTURA-002 | I3: 1240.87 | J3: =I3*507 | K3: =IF(OR(B3="Factura Cliente",B3="Cobro Factura",B3="Depósito Bancario",B3="Inversión",B3="Dividendo",B3="Apertura Inicial"),"Ingreso","Egreso") | L3: Cobrado | M3: BAJA | P3: TRX-00003 | Q3: 45969.189 | R3: SISTEMA | S3: =IF(COUNTIFS($A$2:A2,A3,$F$2:F2,F3,$I$2:I2,I3)>0,"🔴 DUPLICADO EXACTO","") | T3: =IF(AND(A3<>"",B3<>"",D3<>"",E3<>"",I3>0),"✅ OK","❌ FALTA DATO")
A4: 45962 | B4: Apertura Inicial | C4: Efectivo | D4: EMPRESA | E4: Promerica CRC (10000003881708) | F4: Sistema | G4: Balance inicial Promerica CRC | H4: APERTURA-003 | I4: 2.15 | J4: =I4*507 | K4: =IF(OR(B4="Factura Cliente",B4="Cobro Factura",B4="Depósito Bancario",B4="Inversión",B4="Dividendo",B4="Apertura Inicial"),"Ingreso","Egreso") | L4: Cobrado | M4: BAJA | P4: TRX-00004 | Q4: 45969.189 | R4: SISTEMA | S4: =IF(COUNTIFS($A$2:A3,A4,$F$2:F3,F4,$I$2:I3,I4)>0,"🔴 DUPLICADO EXACTO","") | T4: =IF(AND(A4<>"",B4<>"",D4<>"",E4<>"",I4>0),"✅ OK","❌ FALTA DATO")
A5: 45962 | B5: Apertura Inicial | C5: Efectivo | D5: EMPRESA | E5: BNCR CRC (188618-3) | F5: Sistema | G5: Balance inicial BNCR CRC | H5: APERTURA-004 | I5: 59.84 | J5: =I5*507 | K5: =IF(OR(B5="Factura Cliente",B5="Cobro Factura",B5="Depósito Bancario",B5="Inversión",B5="Dividendo",B5="Apertura Inicial"),"Ingreso","Egreso") | L5: Cobrado | M5: BAJA | P5: TRX-00005 | Q5: 45969.189 | R5: SISTEMA | S5: =IF(COUNTIFS($A$2:A4,A5,$F$2:F4,F5,$I$2:I4,I5)>0,"🔴 DUPLICADO EXACTO","") | T5: =IF(AND(A5<>"",B5<>"",D5<>"",E5<>"",I5>0),"✅ OK","❌ FALTA DATO")
A6: 45962 | B6: Apertura Inicial | C6: Ahorro | D6: EMPRESA | E6: BNCR Ahorro 1002335826 | F6: Sistema | G6: Balance inicial ahorro Matrimonio | H6: APERTURA-005 | I6: 1006.06 | J6: =I6*507 | K6: =IF(OR(B6="Factura Cliente",B6="Cobro Factura",B6="Depósito Bancario",B6="Inversión",B6="Dividendo",B6="Apertura Inicial"),"Ingreso","Egreso") | L6: Cobrado | M6: MEDIA | P6: TRX-00006 | Q6: 45969.189 | R6: SISTEMA | S6: =IF(COUNTIFS($A$2:A5,A6,$F$2:F5,F6,$I$2:I5,I6)>0,"🔴 DUPLICADO EXACTO","") | T6: =IF(AND(A6<>"",B6<>"",D6<>"",E6<>"",I6>0),"✅ OK","❌ FALTA DATO")
A7: 45962 | B7: Apertura Inicial | C7: Ahorro | D7: EMPRESA | E7: BNCR Ahorro 1002273441 | F7: Sistema | G7: Balance inicial ahorro Impuestos Municipales | H7: APERTURA-006 | I7: 2263.15 | J7: =I7*507 | K7: =IF(OR(B7="Factura Cliente",B7="Cobro Factura",B7="Depósito Bancario",B7="Inversión",B7="Dividendo",B7="Apertura Inicial"),"Ingreso","Egreso") | L7: Cobrado | M7: MEDIA | P7: TRX-00007 | Q7: 45969.189 | R7: SISTEMA | S7: =IF(COUNTIFS($A$2:A6,A7,$F$2:F6,F7,$I$2:I6,I7)>0,"🔴 DUPLICADO EXACTO","") | T7: =IF(AND(A7<>"",B7<>"",D7<>"",E7<>"",I7>0),"✅ OK","❌ FALTA DATO")
A8: 45962 | B8: Apertura Inicial | C8: Ahorro | D8: EMPRESA | E8: BNCR Ahorro 1002388223 | F8: Sistema | G8: Balance inicial ahorro Black Friday | H8: APERTURA-007 | I8: 225.43 | J8: =I8*507 | K8: =IF(OR(B8="Factura Cliente",B8="Cobro Factura",B8="Depósito Bancario",B8="Inversión",B8="Dividendo",B8="Apertura Inicial"),"Ingreso","Egreso") | L8: Cobrado | M8: MEDIA | P8: TRX-00008 | Q8: 45969.189 | R8: SISTEMA | S8: =IF(COUNTIFS($A$2:A7,A8,$F$2:F7,F8,$I$2:I7,I8)>0,"🔴 DUPLICADO EXACTO","") | T8: =IF(AND(A8<>"",B8<>"",D8<>"",E8<>"",I8>0),"✅ OK","❌ FALTA DATO")
A9: 45962 | B9: Apertura Inicial | C9: Ahorro | D9: EMPRESA | E9: BNCR Ahorro 17000002201 | F9: Sistema | G9: Balance inicial ahorro Vehículo Nuevo | H9: APERTURA-008 | I9: 4559.33 | J9: =I9*507 | K9: =IF(OR(B9="Factura Cliente",B9="Cobro Factura",B9="Depósito Bancario",B9="Inversión",B9="Dividendo",B9="Apertura Inicial"),"Ingreso","Egreso") | L9: Cobrado | M9: MEDIA | P9: TRX-00009 | Q9: 45969.189 | R9: SISTEMA | S9: =IF(COUNTIFS($A$2:A8,A9,$F$2:F8,F9,$I$2:I8,I9)>0,"🔴 DUPLICADO EXACTO","") | T9: =IF(AND(A9<>"",B9<>"",D9<>"",E9<>"",I9>0),"✅ OK","❌ FALTA DATO")
A10: 45962 | B10: Factura Cliente | C10: Servicios | D10: EMPRESA | E10: Promerica USD (40000003881774) | F10: VWR INTERNATIONAL LTDA | G10: Saldo pendiente VWR INTERNATIONAL LTDA | H10: APERTURA-AR-001 | I10: 2800 | J10: =I10*507 | K10: =IF(OR(B10="Factura Cliente",B10="Cobro Factura",B10="Depósito Bancario",B10="Inversión",B10="Dividendo",B10="Apertura Inicial"),"Ingreso","Egreso") | L10: Pendiente | M10: CRÍTICA | P10: TRX-00010 | Q10: 45969.189 | R10: SISTEMA | S10: =IF(COUNTIFS($A$2:A9,A10,$F$2:F9,F10,$I$2:I9,I10)>0,"🔴 DUPLICADO EXACTO","") | T10: =IF(AND(A10<>"",B10<>"",D10<>"",E10<>"",I10>0),"✅ OK","❌ FALTA DATO")
A11: 45962 | B11: Factura Cliente | C11: Servicios | D11: EMPRESA | E11: Promerica USD (40000003881774) | F11: GRUPO ACCION COMERCIAL S.A. | G11: Saldo pendiente GRUPO ACCION COMERCIAL S.A. | H11: APERTURA-AR-002 | I11: 1689.04 | J11: =I11*507 | K11: =IF(OR(B11="Factura Cliente",B11="Cobro Factura",B11="Depósito Bancario",B11="Inversión",B11="Dividendo",B11="Apertura Inicial"),"Ingreso","Egreso") | L11: Pendiente | M11: CRÍTICA | P11: TRX-00011 | Q11: 45969.189 | R11: SISTEMA | S11: =IF(COUNTIFS($A$2:A10,A11,$F$2:F10,F11,$I$2:I10,I11)>0,"🔴 DUPLICADO EXACTO","") | T11: =IF(AND(A11<>"",B11<>"",D11<>"",E11<>"",I11>0),"✅ OK","❌ FALTA DATO")
A12: 45962 | B12: Factura Cliente | C12: Servicios | D12: EMPRESA | E12: Promerica USD (40000003881774) | F12: ALMACEN FISCAL DEL PACIFICO ALFIPAC SOCIEDAD ANONIMA | G12: Saldo pendiente ALMACEN FISCAL DEL PACIFICO ALFIPAC SOCIEDAD ANONIMA | H12: APERTURA-AR-003 | I12: 761.05 | J12: =I12*507 | K12: =IF(OR(B12="Factura Cliente",B12="Cobro Factura",B12="Depósito Bancario",B12="Inversión",B12="Dividendo",B12="Apertura Inicial"),"Ingreso","Egreso") | L12: Pendiente | M12: ALTA | P12: TRX-00012 | Q12: 45969.189 | R12: SISTEMA | S12: =IF(COUNTIFS($A$2:A11,A12,$F$2:F11,F12,$I$2:I11,I12)>0,"🔴 DUPLICADO EXACTO","") | T12: =IF(AND(A12<>"",B12<>"",D12<>"",E12<>"",I12>0),"✅ OK","❌ FALTA DATO")
A13: 45962 | B13: Factura Cliente | C13: Servicios | D13: EMPRESA | E13: Promerica USD (40000003881774) | F13: 3-102-887892 SOCIEDAD DE RESPONSABILIDAD LIMITADA | G13: Saldo pendiente 3-102-887892 SOCIEDAD DE RESPONSABILIDAD LIMITADA | H13: APERTURA-AR-004 | I13: 691.56 | J13: =I13*507 | K13: =IF(OR(B13="Factura Cliente",B13="Cobro Factura",B13="Depósito Bancario",B13="Inversión",B13="Dividendo",B13="Apertura Inicial"),"Ingreso","Egreso") | L13: Pendiente | M13: ALTA | P13: TRX-00013 | Q13: 45969.189 | R13: SISTEMA | S13: =IF(COUNTIFS($A$2:A12,A13,$F$2:F12,F13,$I$2:I12,I13)>0,"🔴 DUPLICADO EXACTO","") | T13: =IF(AND(A13<>"",B13<>"",D13<>"",E13<>"",I13>0),"✅ OK","❌ FALTA DATO")
... A19: 45962 | B19: Factura Cliente | C19: Servicios | D19: EMPRESA | E19: Promerica USD (40000003881774) | F19: CEMSO | G19: Saldo pendiente CEMSO | H19: APERTURA-AR-010 | I19: 333.92 | J19: =I19*507 | K19: =IF(OR(B19="Factura Cliente",B19="Cobro Factura",B19="Depósito Bancario",B19="Inversión",B19="Dividendo",B19="Apertura Inicial"),"Ingreso","Egreso") | L19: Pendiente | M19: MEDIA | P19: TRX-00019 | Q19: 45969.189 | R19: SISTEMA | S19: =IF(COUNTIFS($A$2:A18,A19,$F$2:F18,F19,$I$2:I18,I19)>0,"🔴 DUPLICADO EXACTO","") | T19: =IF(AND(A19<>"",B19<>"",D19<>"",E19<>"",I19>0),"✅ OK","❌ FALTA DATO")
A20: 45929 | B20: Factura Proveedor | C20: Compras | D20: EMPRESA | E20: Promerica USD (40000003881774) | F20: Intcomex | G20: Factura 2502060 - VENCIDA | H20: APERTURA-AP-001 | I20: 410.09 | J20: =I20*507 | K20: =IF(OR(B20="Factura Cliente",B20="Cobro Factura",B20="Depósito Bancario",B20="Inversión",B20="Dividendo",B20="Apertura Inicial"),"Ingreso","Egreso") | L20: Pendiente | M20: CRÍTICA | N20: 45961 | P20: TRX-00020 | Q20: 45969.189 | R20: SISTEMA | S20: =IF(COUNTIFS($A$2:A19,A20,$F$2:F19,F20,$I$2:I19,I20)>0,"🔴 DUPLICADO EXACTO","") | T20: =IF(AND(A20<>"",B20<>"",D20<>"",E20<>"",I20>0),"✅ OK","❌ FALTA DATO")
A21: 45935 | B21: Factura Proveedor | C21: Compras | D21: EMPRESA | E21: Promerica USD (40000003881774) | F21: SEA Global | G21: Factura pendiente - VENCIDA | H21: APERTURA-AP-002 | I21: 44.07 | J21: =I21*507 | K21: =IF(OR(B21="Factura Cliente",B21="Cobro Factura",B21="Depósito Bancario",B21="Inversión",B21="Dividendo",B21="Apertura Inicial"),"Ingreso","Egreso") | L21: Pendiente | M21: CRÍTICA | N21: 45961 | P21: TRX-00021 | Q21: 45969.189 | R21: SISTEMA | S21: =IF(COUNTIFS($A$2:A20,A21,$F$2:F20,F21,$I$2:I20,I21)>0,"🔴 DUPLICADO EXACTO","") | T21: =IF(AND(A21<>"",B21<>"",D21<>"",E21<>"",I21>0),"✅ OK","❌ FALTA DATO")
A22: 45962 | B22: Apertura Inicial | C22: Tarjeta Crédito | D22: EMPRESA | E22: TC BNCR 3519 | F22: BNCR | G22: Saldo tarjeta BNCR - VENCIDA | H22: APERTURA-TC-001 | I22: -1192.44 | J22: =I22*507 | K22: =IF(OR(B22="Factura Cliente",B22="Cobro Factura",B22="Depósito Bancario",B22="Inversión",B22="Dividendo",B22="Apertura Inicial"),"Ingreso","Egreso") | L22: Pendiente | M22: CRÍTICA | P22: TRX-00022 | Q22: 45969.189 | R22: SISTEMA | S22: =IF(COUNTIFS($A$2:A21,A22,$F$2:F21,F22,$I$2:I21,I22)>0,"🔴 DUPLICADO EXACTO","") | T22: =IF(AND(A22<>"",B22<>"",D22<>"",E22<>"",I22>0),"✅ OK","❌ FALTA DATO")
A23: 45962 | B23: Apertura Inicial | C23: Tarjeta Crédito | D23: EMPRESA | E23: TC BNCR 9837 | F23: BNCR | G23: Saldo tarjeta BNCR - VENCIDA | H23: APERTURA-TC-002 | I23: -5779.4 | J23: =I23*507 | K23: =IF(OR(B23="Factura Cliente",B23="Cobro Factura",B23="Depósito Bancario",B23="Inversión",B23="Dividendo",B23="Apertura Inicial"),"Ingreso","Egreso") | L23: Pendiente | M23: CRÍTICA | P23: TRX-00023 | Q23: 45969.189 | R23: SISTEMA | S23: =IF(COUNTIFS($A$2:A22,A23,$F$2:F22,F23,$I$2:I22,I23)>0,"🔴 DUPLICADO EXACTO","") | T23: =IF(AND(A23<>"",B23<>"",D23<>"",E23<>"",I23>0),"✅ OK","❌ FALTA DATO")
A24: 45962 | B24: Apertura Inicial | C24: Tarjeta Crédito | D24: EMPRESA | E24: TC BNCR 6386 | F24: BNCR | G24: Saldo tarjeta BNCR - VENCIDA | H24: APERTURA-TC-003 | I24: -591.7 | J24: =I24*507 | K24: =IF(OR(B24="Factura Cliente",B24="Cobro Factura",B24="Depósito Bancario",B24="Inversión",B24="Dividendo",B24="Apertura Inicial"),"Ingreso","Egreso") | L24: Pendiente | M24: CRÍTICA | P24: TRX-00024 | Q24: 45969.189 | R24: SISTEMA | S24: =IF(COUNTIFS($A$2:A23,A24,$F$2:F23,F24,$I$2:I23,I24)>0,"🔴 DUPLICADO EXACTO","") | T24: =IF(AND(A24<>"",B24<>"",D24<>"",E24<>"",I24>0),"✅ OK","❌ FALTA DATO")
A25: 45962 | B25: Apertura Inicial | C25: Tarjeta Crédito | D25: EMPRESA | E25: TC BNCR 8759 | F25: BNCR | G25: Saldo tarjeta BNCR - VENCIDA | H25: APERTURA-TC-004 | I25: -5731.48 | J25: =I25*507 | K25: =IF(OR(B25="Factura Cliente",B25="Cobro Factura",B25="Depósito Bancario",B25="Inversión",B25="Dividendo",B25="Apertura Inicial"),"Ingreso","Egreso") | L25: Pendiente | M25: CRÍTICA | P25: TRX-00025 | Q25: 45969.189 | R25: SISTEMA | S25: =IF(COUNTIFS($A$2:A24,A25,$F$2:F24,F25,$I$2:I24,I25)>0,"🔴 DUPLICADO EXACTO","") | T25: =IF(AND(A25<>"",B25<>"",D25<>"",E25<>"",I25>0),"✅ OK","❌ FALTA DATO")
A26: 45962 | B26: Apertura Inicial | C26: Tarjeta Crédito | D26: EMPRESA | E26: TC BAC BAC | F26: BAC | G26: Saldo tarjeta BAC - Activa | H26: APERTURA-TC-005 | I26: -3087.67 | J26: =I26*507 | K26: =IF(OR(B26="Factura Cliente",B26="Cobro Factura",B26="Depósito Bancario",B26="Inversión",B26="Dividendo",B26="Apertura Inicial"),"Ingreso","Egreso") | L26: Pendiente | M26: ALTA | P26: TRX-00026 | Q26: 45969.189 | R26: SISTEMA | S26: =IF(COUNTIFS($A$2:A25,A26,$F$2:F25,F26,$I$2:I25,I26)>0,"🔴 DUPLICADO EXACTO","") | T26: =IF(AND(A26<>"",B26<>"",D26<>"",E26<>"",I26>0),"✅ OK","❌ FALTA DATO")

Sheet Dashboard
A1: DASHBOARD FINANCIERO
A3: Métrica | B3: Valor USD | C3: Valor CRC | D3: Estado
A4: Efectivo Total | B4: =SUMIFS(TRANSACCIONES!$I:$I,TRANSACCIONES!$C:$C,"Efectivo",TRANSACCIONES!$L:$L,"Cobrado") | C4: =B4*507
A5: Cuentas por Cobrar | B5: =SUMIFS(TRANSACCIONES!$I:$I,TRANSACCIONES!$B:$B,"Factura Cliente",TRANSACCIONES!$L:$L,"Pendiente") | C5: =B5*507
A6: Cuentas por Pagar | B6: =SUMIFS(TRANSACCIONES!$I:$I,TRANSACCIONES!$B:$B,"Factura Proveedor",TRANSACCIONES!$L:$L,"Pendiente") | C6: =B6*507
A7: Tarjetas Crédito | B7: =SUMIFS(TRANSACCIONES!$I:$I,TRANSACCIONES!$C:$C,"Tarjeta Crédito") | C7: =B7*507

Sheet Efectivo
A1: ESTADO DE EFECTIVO
A2: Fecha | B2: Concepto | C2: Cuenta | D2: Ingreso | E2: Egreso | F2: Balance
A3: =TRANSACCIONES!A2 | B3: =TRANSACCIONES!G2 | C3: =TRANSACCIONES!E2 | D3: =IF(TRANSACCIONES!K2="Ingreso",TRANSACCIONES!I2,"") | E3: =IF(TRANSACCIONES!K2="Egreso",TRANSACCIONES!I2,"") | F3: =SUM(D3:D3)-SUM(E3:E3)

Sheet A_R
A1: CUENTAS POR COBRAR
A2: Cliente | B2: Factura | C2: Fecha | D2: Monto | E2: Estado | F2: Prioridad | G2: Días Mora

Sheet A_P
A1: CUENTAS POR PAGAR

Sheet Tarjetas_Credito
A1: TARJETAS DE CRÉDITO

Sheet Conciliacion
A1: CONCILIACIÓN BANCARIA

Sheet Auditoria
A1: LOG DE AUDITORÍA

Sheet Health_Check
A1: HEALTH CHECK DEL SISTEMA
A3: Check | B3: Estado | C3: Detalles
A4: Fórmulas intactas | B4: =IF(COUNTBLANK(TRANSACCIONES!K:K)=0,"✅ OK","❌ ERROR") | C4: Verificar columna K
A5: Sin duplicados | B5: =IF(COUNTIF(TRANSACCIONES!S:S,"*DUPLICADO*")=0,"✅ OK","⚠️ DUPLICADOS") | C5: Revisar columna S
A6: Balance contable | B6: =IF(ABS(Dashboard!B4-(Dashboard!B5-Dashboard!B6))<1,"✅ OK","❌ DESCUADRE") | C6: Efectivo vs A/R-A/P
